trendPredict_zhaozl/__init__.py
trendPredict_zhaozl/__version__.py
trendPredict_zhaozl/core.py
trendPredict-1.0.dist-info/LICENSE
trendPredict-1.0.dist-info/METADATA
trendPredict-1.0.dist-info/WHEEL
trendPredict-1.0.dist-info/top_level.txt
trendPredict-1.0.dist-info/RECORD
