Metadata-Version: 2.1
Name: trendPredict
Version: 1.0
Summary: Trend predict by zhaozl.
Home-page: https://pypi.org/manage/projects/
Author: zhaozl
Author-email: 545362989@qq.com
License: MIT
Platform: UNKNOWN
Classifier: License :: OSI Approved :: MIT License
Classifier: Programming Language :: Python
Classifier: Programming Language :: Python :: 3
Classifier: Programming Language :: Python :: 3.6
Classifier: Programming Language :: Python :: Implementation :: CPython
Classifier: Programming Language :: Python :: Implementation :: PyPy
Requires-Python: >=3.7.0
